sen-chatbot/ChatBot.py
sen_chatbot/ChatBot.py
sen_chatbot-1.0.2.dist-info/LICENSE
sen_chatbot-1.0.2.dist-info/METADATA
sen_chatbot-1.0.2.dist-info/WHEEL
sen_chatbot-1.0.2.dist-info/top_level.txt
sen_chatbot-1.0.2.dist-info/RECORD
