Metadata-Version: 2.1
Name: sen-chatbot
Version: 1.0.2
Summary: A Python package for creating chatbot.
Home-page: https://github.com/bubai666sen/sen-chatbot
Author: Sourav Sen
Author-email: bubai666sen@gmail.com
License: MIT
Platform: UNKNOWN
Classifier: License :: OSI Approved :: MIT License
Classifier: Programming Language :: Python :: 3
Classifier: Programming Language :: Python :: 3.7
Requires-Dist: wikipedia
